easybird/__init__.py
easybird/detection.py
easybird/models/jit_bad.pt
easybird-0.0.3.dist-info/LICENSE
easybird-0.0.3.dist-info/METADATA
easybird-0.0.3.dist-info/WHEEL
easybird-0.0.3.dist-info/top_level.txt
easybird-0.0.3.dist-info/RECORD
