Metadata-Version: 2.1
Name: easybird
Version: 0.0.3
Summary: A python toolkit for Bird Activity Detection (BAD)
Home-page: https://github.com/realzza/easybird
Author: Ziang Zhou
Author-email: ziang.zhou518@gmail.com
License: UNKNOWN
Project-URL: Bug Tracker, https://github.com/realzza/easybird/issues
Platform: UNKNOWN
Classifier: Programming Language :: Python :: 3
Classifier: License :: OSI Approved :: MIT License
Classifier: Operating System :: OS Independent
Requires-Python: >=3.6
License-File: LICENSE
Requires-Dist: audiofile
Requires-Dist: torch
Requires-Dist: torchaudio
Requires-Dist: torchvision
Requires-Dist: soxr
Requires-Dist: tqdm
Requires-Dist: scipy
Requires-Dist: python-speech-features
